wbn/__init__.py
wbn/classifier.py
wbn/config.py
wbn/errors.py
wbn/object.py
wbn/sample/__init__.py
wbn/sample/datasets.py
wbn-0.1.0.dist-info/AUTHORS.rst
wbn-0.1.0.dist-info/LICENSE
wbn-0.1.0.dist-info/METADATA
wbn-0.1.0.dist-info/WHEEL
wbn-0.1.0.dist-info/entry_points.txt
wbn-0.1.0.dist-info/top_level.txt
wbn-0.1.0.dist-info/RECORD
