Metadata-Version: 2.1
Name: wbn
Version: 0.1.0
Summary: Weighted Bayesian Network Text Classification
Home-page: https://github.com/leonkozlowski/wbn
Author: Leon Kozlowski
Author-email: leonkozlowski@gmail.com
License: MIT license
Keywords: wbn
Platform: UNKNOWN
Classifier: Development Status :: 2 - Pre-Alpha
Classifier: Intended Audience :: Developers
Classifier: License :: OSI Approved :: MIT License
Classifier: Natural Language :: English
Classifier: Programming Language :: Python :: 3
Classifier: Programming Language :: Python :: 3.6
Classifier: Programming Language :: Python :: 3.7
Classifier: Programming Language :: Python :: 3.8
Requires-Python: >=3.6
Requires-Dist: Click (>=7.0)
Requires-Dist: networkx (>=2.5)
Requires-Dist: nltk (>=3.5)
Requires-Dist: numpy (>=1.19.4)
